cardstock/CardStock_Designer_mac.spec
cardstock/__init__.py
cardstock/__main__.py
cardstock/allCodeWindow.py
cardstock/analyzer.py
cardstock/appCommands.py
cardstock/build.py
cardstock/cardstockFrameParts.py
cardstock/codeInspector.py
cardstock/codeInspectorMulti.py
cardstock/codeRunnerThread.py
cardstock/consoleWindow.py
cardstock/controlPanel.py
cardstock/designer.py
cardstock/easing.py
cardstock/embeddedImages.py
cardstock/errorListWindow.py
cardstock/findEngineDesigner.py
cardstock/findEngineViewer.py
cardstock/flippedGCDC.py
cardstock/generator.py
cardstock/helpData.py
cardstock/helpDataGen.py
cardstock/helpDialogs.py
cardstock/imageFactory.py
cardstock/mediaSearchDialogs.py
cardstock/migrations.py
cardstock/propertyInspector.py
cardstock/pythonEditor.py
cardstock/resourcePathManager.py
cardstock/runner.py
cardstock/sanitizer.py
cardstock/simpleListBox.py
cardstock/stackExporter.py
cardstock/stackManager.py
cardstock/stackModel.py
cardstock/standalone.py
cardstock/tones.py
cardstock/tools.py
cardstock/uiButton.py
cardstock/uiCard.py
cardstock/uiGroup.py
cardstock/uiImage.py
cardstock/uiShape.py
cardstock/uiTextBase.py
cardstock/uiTextField.py
cardstock/uiTextLabel.py
cardstock/uiView.py
cardstock/uiWebView.py
cardstock/variablesWindow.py
cardstock/version.py
cardstock/viewer.py
cardstock/examples/Asteroids.cds
cardstock/examples/Browser.cds
cardstock/examples/Calculator.cds
cardstock/examples/Catch.cds
cardstock/examples/Diary.cds
cardstock/examples/Dice-stats.cds
cardstock/examples/Dice.cds
cardstock/examples/Factor.cds
cardstock/examples/Fifteen.cds
cardstock/examples/Flappy.cds
cardstock/examples/Graph.cds
cardstock/examples/Guess.cds
cardstock/examples/Hanoi.cds
cardstock/examples/Logo.cds
cardstock/examples/Magic.cds
cardstock/examples/Mastermind.cds
cardstock/examples/Maze.cds
cardstock/examples/Morph.cds
cardstock/examples/Navigation.cds
cardstock/examples/Number-puzzle.cds
cardstock/examples/Piano.cds
cardstock/examples/Pong.cds
cardstock-0.99.9.dist-info/licenses/LICENSE
cardstock-0.99.9.dist-info/METADATA
cardstock-0.99.9.dist-info/WHEEL
cardstock-0.99.9.dist-info/entry_points.txt
cardstock-0.99.9.dist-info/top_level.txt
cardstock-0.99.9.dist-info/RECORD
