Metadata-Version: 2.4
Name: cardstock
Version: 0.99.9
Summary: A simple development and rapid prototyping tool for quickly building multi-platform desktop programs and web apps.
Home-page: https://github.com/benjie-git/CardStock/wiki
Author: Ben Levitt
Author-email: benjie@gmail.com
Classifier: Programming Language :: Python :: 3.12
Classifier: License :: OSI Approved :: Mozilla Public License 2.0 (MPL 2.0)
Classifier: Operating System :: OS Independent
Requires-Python: <=3.12,>=3.9
License-File: LICENSE
Requires-Dist: attrdict3
Requires-Dist: wxpython>=4.2.2
Requires-Dist: PyInstaller==5.13.2
Requires-Dist: requests==2.31.0
Requires-Dist: numpy==2.2.6
Requires-Dist: simpleaudio-312compat
Provides-Extra: mp3
Requires-Dist: streamp3-313compat; extra == "mp3"
Dynamic: license-file
